tibo/__init__.py
tibo/cli.py
tibo/utils.py
tibo/agent/__init__.py
tibo/agent/agent.py
tibo/agent/claude_agent.py
tibo/agent/tools/__init__.py
tibo/agent/tools/codebase_intteligence.py
tibo/agent/tools/file_tool.py
tibo/agent/tools/search_tool.py
tibo/agent/tools/terminal_tool.py
tibo/agent/tools/tool_schemas.py
tibo/config/__init__.py
tibo/config/config.py
tibo/fetching/__init__.py
tibo/fetching/fetching.py
tibo/fetching/refinement.py
tibo/indexing/__init__.py
tibo/indexing/indexing.py
tibo/indexing/vector_db.py
tibo/indexing/call_graph_utils/__init__.py
tibo/indexing/call_graph_utils/call_graph.py
tibo/indexing/call_graph_utils/python/ParserClassPY.py
tibo/indexing/call_graph_utils/python/__init__.py
tibo/indexing/call_graph_utils/python/call_graph_py.py
tibo/indexing/call_graph_utils/typescript/ParserClassTS.py
tibo/indexing/call_graph_utils/typescript/__init__.py
tibo/indexing/call_graph_utils/typescript/call_graph_ts.py
tibo/indexing/call_graph_utils/typescript/build/typescript.so
tibo/indexing/chunking/__init__.py
tibo/indexing/chunking/chunking.py
tibo/indexing/chunking/llm_pass.py
tibo/indexing/chunking/python/ChunkingPython.py
tibo/indexing/chunking/python/__init__.py
tibo/indexing/chunking/python/chunk_python.py
tibo/indexing/chunking/typescript/ChunkingTypescript.py
tibo/indexing/chunking/typescript/__init__.py
tibo/indexing/chunking/typescript/chunk_typescript.py
tibo-1.1.3.dist-info/METADATA
tibo-1.1.3.dist-info/WHEEL
tibo-1.1.3.dist-info/entry_points.txt
tibo-1.1.3.dist-info/top_level.txt
tibo-1.1.3.dist-info/RECORD
